packageEVS/__init__.py
packageEVS/db_operations.py
packageevs-0.2.0.dist-info/METADATA
packageevs-0.2.0.dist-info/WHEEL
packageevs-0.2.0.dist-info/top_level.txt
packageevs-0.2.0.dist-info/RECORD
